mmflow/__init__.py
mmflow/version.py
mmflow/.mim/model-index.yml
mmflow/.mim/configs/_base_/default_runtime.py
mmflow/.mim/configs/_base_/datasets/chairssdhom_384x448.py
mmflow/.mim/configs/_base_/datasets/flyingchairs_320x448.py
mmflow/.mim/configs/_base_/datasets/flyingchairs_384x448.py
mmflow/.mim/configs/_base_/datasets/flyingchairs_raft_368x496.py
mmflow/.mim/configs/_base_/datasets/flyingchairsocc_bi_occ_384x448.py
mmflow/.mim/configs/_base_/datasets/flyingthings3d_raft_400x720.py
mmflow/.mim/configs/_base_/datasets/flyingthings3d_subset_384x768.py
mmflow/.mim/configs/_base_/datasets/flyingthings3d_subset_bi_with_occ_384x768.py
mmflow/.mim/configs/_base_/datasets/flyingthings3d_subset_chairssdhom_384x448.py
mmflow/.mim/configs/_base_/datasets/kitti2012_kitti2015_320x896.py
mmflow/.mim/configs/_base_/datasets/kitti2012_kitti2015_irr_320x896.py
mmflow/.mim/configs/_base_/datasets/kitti2012_kitti2015_test.py
mmflow/.mim/configs/_base_/datasets/kitti2015_raft_288x960.py
mmflow/.mim/configs/_base_/datasets/kitti2015_raft_test.py
mmflow/.mim/configs/_base_/datasets/sintel_384x768.py
mmflow/.mim/configs/_base_/datasets/sintel_cleanx100_sintel_fianlx100_flyingthings3d_raft_368x768.py
mmflow/.mim/configs/_base_/datasets/sintel_cleanx100_sintel_fianlx100_kitti2015x200_hd1kx5_flyingthings3d_raft_384x768.py
mmflow/.mim/configs/_base_/datasets/sintel_final_384x768.py
mmflow/.mim/configs/_base_/datasets/sintel_final_irr_with_occ_384x768.py
mmflow/.mim/configs/_base_/datasets/sintel_final_pwcnet_384x768.py
mmflow/.mim/configs/_base_/datasets/sintel_irr_with_occ_384x768.py
mmflow/.mim/configs/_base_/datasets/sintel_kitti2015_hd1k_320x768.py
mmflow/.mim/configs/_base_/datasets/sintel_kitti2015_hd1k_maskflownet_320x768.py
mmflow/.mim/configs/_base_/datasets/sintel_kitti_liteflownet2_320x768.py
mmflow/.mim/configs/_base_/datasets/sintel_liteflownet_384x768.py
mmflow/.mim/configs/_base_/datasets/sintel_pwcnet_384x768.py
mmflow/.mim/configs/_base_/models/flownetc.py
mmflow-0.5.2.dist-info/LICENSE
mmflow-0.5.2.dist-info/METADATA
mmflow-0.5.2.dist-info/WHEEL
mmflow-0.5.2.dist-info/top_level.txt
mmflow-0.5.2.dist-info/RECORD
