Metadata-Version: 2.1
Name: mmflow
Version: 0.5.2
Summary: OpenMMLab Optical flow Toolbox and Benchmark
Home-page: https://github.com/open-mmlab/mmflow
Author: MMFlow Contributors
Author-email: openmmlab@gmail.com
License: Apache License 2.0
Keywords: computer vision,optical flow
Platform: UNKNOWN
Classifier: Development Status :: 4 - Beta
Classifier: License :: OSI Approved :: Apache Software License
Classifier: Operating System :: OS Independent
Classifier: Programming Language :: Python :: 3
Classifier: Programming Language :: Python :: 3.6
Classifier: Programming Language :: Python :: 3.7
Classifier: Programming Language :: Python :: 3.8
Requires-Dist: matplotlib
Requires-Dist: numpy
Requires-Dist: six
Provides-Extra: all
Requires-Dist: numpy ; extra == 'all'
Requires-Dist: scikit-learn ; extra == 'all'
Requires-Dist: scipy ; extra == 'all'
Requires-Dist: matplotlib ; extra == 'all'
Requires-Dist: six ; extra == 'all'
Requires-Dist: asynctest ; extra == 'all'
Requires-Dist: codecov ; extra == 'all'
Requires-Dist: coverage ; extra == 'all'
Requires-Dist: flake8 ; extra == 'all'
Requires-Dist: interrogate ; extra == 'all'
Requires-Dist: kwarray ; extra == 'all'
Requires-Dist: pytest ; extra == 'all'
Requires-Dist: ubelt ; extra == 'all'
Requires-Dist: xdoctest (>=0.10.0) ; extra == 'all'
Requires-Dist: yapf ; extra == 'all'
Provides-Extra: build
Requires-Dist: numpy ; extra == 'build'
Provides-Extra: mim
Requires-Dist: mmcv-full (<1.7.0,>=1.3.15) ; extra == 'mim'
Provides-Extra: optional
Requires-Dist: scikit-learn ; extra == 'optional'
Requires-Dist: scipy ; extra == 'optional'
Provides-Extra: tests
Requires-Dist: asynctest ; extra == 'tests'
Requires-Dist: codecov ; extra == 'tests'
Requires-Dist: coverage ; extra == 'tests'
Requires-Dist: flake8 ; extra == 'tests'
Requires-Dist: interrogate ; extra == 'tests'
Requires-Dist: kwarray ; extra == 'tests'
Requires-Dist: matplotlib ; extra == 'tests'
Requires-Dist: pytest ; extra == 'tests'
Requires-Dist: ubelt ; extra == 'tests'
Requires-Dist: xdoctest (>=0.10.0) ; extra == 'tests'
Requires-Dist: yapf ; extra == 'tests'
